python_xirsys/__init__.py
python_xirsys/connection.py
python_xirsys/exceptions.py
python_xirsys/objects.py
python_xirsys-0.1.1.dist-info/DESCRIPTION.rst
python_xirsys-0.1.1.dist-info/METADATA
python_xirsys-0.1.1.dist-info/RECORD
python_xirsys-0.1.1.dist-info/WHEEL
python_xirsys-0.1.1.dist-info/metadata.json
python_xirsys-0.1.1.dist-info/top_level.txt
