Metadata-Version: 2.0
Name: python-xirsys
Version: 0.1.1
Summary: A Python 3 interface to the XirSys API.
Home-page: https://github.com/kavdev/python-xirsys/
Author: Alexander Kavanaugh
Author-email: alex@kavdev.io
License: License :: OSI Approved :: MIT License
Keywords: xirsys
Platform: UNKNOWN
Classifier: Development Status :: 3 - Alpha
Classifier: Intended Audience :: Developers
Classifier: License :: OSI Approved :: MIT License
Classifier: Natural Language :: English
Classifier: Programming Language :: Python :: 3.4
Classifier: Programming Language :: Python :: 3.5
Classifier: Programming Language :: Python :: 3 :: Only
Requires-Dist: requests (~=2.10)
